email_notifications/__init__.py
email_notifications/admin.py
email_notifications/apps.py
email_notifications/forms.py
email_notifications/models.py
email_notifications/services.py
email_notifications/signals.py
email_notifications/tests.py
email_notifications/validators.py
email_notifications/views.py
email_notifications/migrations/0001_initial.py
email_notifications/migrations/__init__.py
email_notifications/templates/email-notifications/unsubscribe.html
email_notifications/templates/email-notifications/unsubscribe_done.html
ponddy_email_notification-0.0.6.dist-info/METADATA
ponddy_email_notification-0.0.6.dist-info/WHEEL
ponddy_email_notification-0.0.6.dist-info/top_level.txt
ponddy_email_notification-0.0.6.dist-info/RECORD
