Metadata-Version: 2.1
Name: ponddy-email-notification
Version: 0.0.6
Summary: Ponddy email notification package
Home-page: https://github.com/ponddy-edu/ponddy-email-notification
Author: Arthur Chang
Author-email: arthurc0102@gmail.com
License: UNKNOWN
Keywords: ponddy
Platform: UNKNOWN
Classifier: Programming Language :: Python :: 3
Requires-Dist: django
